py3dgraphics/__init__.py
py3dgraphics/editor.py
py3dgraphics/graphics.py
py3dgraphics/opengl_graphics.py
py3dgraphics/physics_scene.py
py3dgraphics/qt_editor.py
py3dgraphics/treeed.py
py3dgraphics/utils.py
treeed-0.3.2.1.dist-info/METADATA
treeed-0.3.2.1.dist-info/WHEEL
treeed-0.3.2.1.dist-info/top_level.txt
treeed-0.3.2.1.dist-info/RECORD
