Metadata-Version: 2.4
Name: Treeed
Version: 0.3.2.1
Summary: Библиотека для создания и отображения 3D объектов с помощью PyOpenGL и Pygame
Home-page: 
Author: Umar
Author-email: umarfrost2011@gmail.com
Classifier: Development Status :: 3 - Alpha
Classifier: Intended Audience :: Developers
Classifier: License :: OSI Approved :: MIT License
Classifier: Operating System :: OS Independent
Classifier: Programming Language :: Python :: 3
Classifier: Programming Language :: Python :: 3.6
Classifier: Programming Language :: Python :: 3.7
Classifier: Programming Language :: Python :: 3.8
Classifier: Programming Language :: Python :: 3.9
Classifier: Programming Language :: Python :: 3.10
Requires-Python: >=3.6
Requires-Dist: numpy
Provides-Extra: opengl
Requires-Dist: pygame; extra == "opengl"
Requires-Dist: PyOpenGL; extra == "opengl"
Requires-Dist: PyOpenGL-accelerate; extra == "opengl"
Provides-Extra: physics
Requires-Dist: pybullet; extra == "physics"
Provides-Extra: qt
Requires-Dist: PyQt5; extra == "qt"
Provides-Extra: all
Requires-Dist: pygame; extra == "all"
Requires-Dist: PyOpenGL; extra == "all"
Requires-Dist: PyOpenGL-accelerate; extra == "all"
Requires-Dist: PyQt5; extra == "all"
Dynamic: author
Dynamic: author-email
Dynamic: classifier
Dynamic: description
Dynamic: description-content-type
Dynamic: provides-extra
Dynamic: requires-dist
Dynamic: requires-python
Dynamic: summary
